django_rq/__init__.py
django_rq/admin.py
django_rq/apps.py
django_rq/decorators.py
django_rq/jobs.py
django_rq/models.py
django_rq/queues.py
django_rq/settings.py
django_rq/thread_queue.py
django_rq/urls.py
django_rq/utils.py
django_rq/views.py
django_rq/workers.py
django_rq/management/__init__.py
django_rq/management/commands/__init__.py
django_rq/management/commands/rqenqueue.py
django_rq/management/commands/rqresume.py
django_rq/management/commands/rqscheduler.py
django_rq/management/commands/rqstats.py
django_rq/management/commands/rqsuspend.py
django_rq/management/commands/rqworker-pool.py
django_rq/management/commands/rqworker.py
django_rq/migrations/0001_initial.py
django_rq/migrations/__init__.py
django_rq/templates/django_rq/clear_failed_queue.html
django_rq/templates/django_rq/clear_queue.html
django_rq/templates/django_rq/confirm_action.html
django_rq/templates/django_rq/delete_job.html
django_rq/templates/django_rq/failed_jobs.html
django_rq/templates/django_rq/finished_jobs.html
django_rq/templates/django_rq/index.html
django_rq/templates/django_rq/job_detail.html
django_rq/templates/django_rq/jobs.html
django_rq/templates/django_rq/requeue_all.html
django_rq/templates/django_rq/scheduler.html
django_rq/templates/django_rq/started_job_registry.html
django_rq/templates/django_rq/stats.html
django_rq/templates/django_rq/test.html
django_rq/templates/django_rq/worker_details.html
django_rq/templates/django_rq/workers.html
django_rq/templatetags/__init__.py
django_rq/templatetags/django_rq.py
django_rq/templatetags/jquery_path.py
django_rq/tests/__init__.py
django_rq/tests/fixtures.py
django_rq/tests/settings.py
django_rq/tests/test_views.py
django_rq/tests/tests.py
django_rq/tests/urls.py
django_rq/tests/utils.py
django_rq/tests/views.py
django_rq-3.0.0.dist-info/LICENSE.txt
django_rq-3.0.0.dist-info/METADATA
django_rq-3.0.0.dist-info/WHEEL
django_rq-3.0.0.dist-info/top_level.txt
django_rq-3.0.0.dist-info/RECORD
